AUTHORS
LICENSE
NEWS
README.md
gareth/_version.py
gareth/gareth.py
gareth-0.1.0.dist-info/entry_points.txt
gareth-0.1.0.dist-info/LICENSE
gareth-0.1.0.dist-info/WHEEL
gareth-0.1.0.dist-info/METADATA
gareth-0.1.0.dist-info/RECORD
