Metadata-Version: 2.1
Name: gareth
Version: 0.1.0
Summary: Tool to automate the developer setup of GrimoireLab
License: GPL-3.0-or-later
Author: Venu Vardhan Reddy Tekula
Author-email: venu@bitergia.com
Requires-Python: >=3.6,<4.0
Classifier: License :: OSI Approved :: GNU General Public License v3 or later (GPLv3+)
Classifier: Programming Language :: Python :: 3
Classifier: Programming Language :: Python :: 3.6
Classifier: Programming Language :: Python :: 3.7
Classifier: Programming Language :: Python :: 3.8
Classifier: Programming Language :: Python :: 3.9
Requires-Dist: GitPython (>=3.1.15,<4.0.0)
Requires-Dist: PyGithub (>=1.55,<2.0)
Requires-Dist: click (>=7.1.2,<8.0.0)
